ossi_tool/__init__.py
ossi_tool/__main__.py
ossi_tool/ossit.py
ossi_tool/pxsshmod.py
ossi_tool-0.3.3.6.dist-info/LICENSE
ossi_tool-0.3.3.6.dist-info/METADATA
ossi_tool-0.3.3.6.dist-info/WHEEL
ossi_tool-0.3.3.6.dist-info/entry_points.txt
ossi_tool-0.3.3.6.dist-info/top_level.txt
ossi_tool-0.3.3.6.dist-info/RECORD
