Metadata-Version: 2.1
Name: ossi-tool
Version: 0.3.3.6
Summary: Tool to creact CSV output from Avaya Communcation Manager commands.
Home-page: https://github.com/deesnow/ossi_tool
Author: Janos Tarjanyi
Author-email: janos.tarajnyi@gmail.com
License: ISC
Platform: UNKNOWN
Classifier: Development Status :: 3 - Alpha
Classifier: Environment :: Console
Classifier: Programming Language :: Python :: 2.7
Classifier: Intended Audience :: Telecommunications Industry
Classifier: Topic :: Communications :: Telephony
Requires-Dist: pexpect
